Cortex_Runner-1.0.1.dist-info/DESCRIPTION.rst
Cortex_Runner-1.0.1.dist-info/METADATA
Cortex_Runner-1.0.1.dist-info/RECORD
Cortex_Runner-1.0.1.dist-info/WHEEL
Cortex_Runner-1.0.1.dist-info/metadata.json
Cortex_Runner-1.0.1.dist-info/top_level.txt
cortexrunner/__init__.py
cortexrunner/api.py
